tabNamesCat/__init__.py
tabNamesCat/main.py
tabNamesCat/model.pkl
tabNamesCat/vector.pkl
tabNamesCat-0.1.4.dist-info/LICENSE
tabNamesCat-0.1.4.dist-info/METADATA
tabNamesCat-0.1.4.dist-info/WHEEL
tabNamesCat-0.1.4.dist-info/top_level.txt
tabNamesCat-0.1.4.dist-info/RECORD
