Metadata-Version: 2.1
Name: tabNamesCat
Version: 0.1.4
Summary: CategorizationTabNames
Home-page: https://github.com/Denisalik/TabNamesCat
Author: Denisalik
Author-email: schgletovdenis@mail.ru
License: MIT
Classifier: Development Status :: 3 - Alpha
Classifier: Intended Audience :: Science/Research
Classifier: License :: OSI Approved :: MIT License
Classifier: Programming Language :: Python :: 3
Classifier: Programming Language :: Python :: 3.4
Classifier: Programming Language :: Python :: 3.5
Classifier: Programming Language :: Python :: 3.6
Classifier: Programming Language :: Python :: 3.7
Classifier: Programming Language :: Python :: 3.8
Classifier: Programming Language :: Python :: 3.9
Classifier: Programming Language :: Python :: 3.10
License-File: LICENSE
Requires-Dist: scikit-learn
Requires-Dist: langdetect
Requires-Dist: nltk
